aqlm/__init__.py
aqlm/inference.py
aqlm/utils.py
aqlm/inference_kernels/__init__.py
aqlm/inference_kernels/cuda_kernel.cpp
aqlm/inference_kernels/cuda_kernel.cu
aqlm/inference_kernels/cuda_kernel.py
aqlm/inference_kernels/dequantization.py
aqlm/inference_kernels/kernel_selector.py
aqlm/inference_kernels/numba_kernel.py
aqlm/inference_kernels/triton_kernel.py
aqlm-1.1.7.dist-info/METADATA
aqlm-1.1.7.dist-info/WHEEL
aqlm-1.1.7.dist-info/top_level.txt
aqlm-1.1.7.dist-info/RECORD
