Metadata-Version: 2.4
Name: aqlm
Version: 1.1.7
Summary: Efficiently run models quantized with AQLM
Home-page: https://github.com/Vahe1994/AQLM
Author: AQLM paper authors
Author-email: vahe527887@yandex.ru
Project-URL: Bug Tracker, https://github.com/Vahe1994/AQLM/issues
Classifier: Development Status :: 4 - Beta
Classifier: Intended Audience :: Developers
Classifier: Intended Audience :: Science/Research
Classifier: License :: OSI Approved :: MIT License
Classifier: Programming Language :: Python :: 3
Classifier: Programming Language :: Python :: 3.8
Classifier: Programming Language :: Python :: 3.9
Classifier: Programming Language :: Python :: 3.10
Classifier: Programming Language :: Python :: 3.11
Classifier: Topic :: Scientific/Engineering
Classifier: Topic :: Scientific/Engineering :: Mathematics
Classifier: Topic :: Scientific/Engineering :: Artificial Intelligence
Classifier: Topic :: Software Development
Classifier: Topic :: Software Development :: Libraries
Classifier: Topic :: Software Development :: Libraries :: Python Modules
Requires-Python: >=3.8
Requires-Dist: torch>=2.2.0
Requires-Dist: transformers>=4.38.0
Requires-Dist: accelerate>=0.27.0
Provides-Extra: gpu
Requires-Dist: triton>=2.1; extra == "gpu"
Requires-Dist: ninja; extra == "gpu"
Provides-Extra: cpu
Requires-Dist: numba>=0.56.4; extra == "cpu"
Requires-Dist: scipy>=1.11.3; extra == "cpu"
Provides-Extra: dev
Requires-Dist: pytest==6.2.5; extra == "dev"
Requires-Dist: pytest-forked; extra == "dev"
Requires-Dist: pytest-asyncio==0.16.0; extra == "dev"
Requires-Dist: black==22.3.0; extra == "dev"
Requires-Dist: isort==5.13.2; extra == "dev"
